helperagent.py
helperagent-5.0.0.dist-info/LICENSE.txt
helperagent-5.0.0.dist-info/METADATA
helperagent-5.0.0.dist-info/WHEEL
helperagent-5.0.0.dist-info/top_level.txt
helperagent-5.0.0.dist-info/RECORD
